api_youtube/__init__.py
api_youtube/channel.py
api_youtube/video.py
api_youtube-0.1.dist-info/METADATA
api_youtube-0.1.dist-info/WHEEL
api_youtube-0.1.dist-info/top_level.txt
api_youtube-0.1.dist-info/RECORD
